Workbook

Sheet Raw Data
A1: Raw Data
B3: India - IT Services (Rs. Crore)
B4: S.No. | C4: Name | D4: CMP Rs. | E4: No. Eq. Shares Cr. | F4: Mar Cap Rs.Cr. | G4: Debt Rs.Cr. | H4: Cash Rs.Cr. | I4: Net Debt | J4: EV Rs.Cr. | K4: Sales Rs.Cr. | L4: EV/EBITDA (input) | M4: EBITDA (derived) | N4: PAT 12M Rs.Cr. | O4: Book Value/Share | P4: P/E (input)
B5: 1 | C5: TCS | D5: 2361 | E5: =F5/D5 -> 361.80856 | F5: 854230 | G5: 10821 | H5: 56743 | I5: =G5-H5 -> -45922 | J5: =F5+I5 -> 808308 | K5: 275859 | L5: 11.74 | M5: =J5/L5 -> 68850.767 | N5: 50055 | O5: 296 | P5: 15.9
B6: 2 | C6: Infosys | D6: 1169.2 | E6: =F6/D6 -> 405.80568 | F6: 474468 | G6: 8788 | H6: 26822 | I6: =G6-H6 -> -18034 | J6: =F6+I6 -> 456434 | K6: 184582 | L6: 9.32 | M6: =J6/L6 -> 48973.605 | N6: 30325 | O6: 228.68 | P6: 15.22
B7: 3 | C7: Wipro Ltd | D7: 184 | E7: =F7/D7 -> 990.44022 | F7: 182241 | G7: 20291 | H7: 54324 | I7: =G7-H7 -> -34033 | J7: =F7+I7 -> 148208 | K7: 94968 | L7: 10.12 | M7: =J7/L7 -> 14645.059 | N7: 13285 | O7: 83.9 | P7: 16.22
B10: US - Technology Mega-caps ($ Million)
B11: Company Name | C11: Ticker | D11: Currency | E11: Share Price | F11: Outstanding Shares | G11: Equity Value | H11: Total Debt | I11: Net Debt | J11: Enterprise Value | K11: CY2026 Revenue | L11: CY2026 EBITDA | M11: CY2026 Net Income | N11: Book Value/Share | O11: EV/Revenue | P11: EV/EBITDA | Q11: P/E | R11: P/B
B12: Alphabet Inc. | C12: GOOGL | D12: USD | E12: 356.13 | F12: 12230 | G12: =F12*E12 -> 4355469.9 | H12: 120790 | I12: =120790-242470 -> -121680 | J12: =G12+I12 -> 4233789.9 | K12: 497700 | L12: 173200 | M12: 175134 | N12: 50.9 | O12: =J12/K12 -> 8.5067107 | P12: =J12/L12 -> 24.444514 | Q12: =E12/(M12/F12) -> 24.869357 | R12: =E12/N12 -> 6.9966601
B13: Microsoft Corporation | C13: MSFT | D13: USD | E13: 464.72 | F13: 7427 | G13: =F13*E13 -> 3451475.4 | H13: 128813 | I13: =128813-76843 -> 51970 | J13: =G13+I13 -> 3503445.4 | K13: 331840 | L13: 217300 | M13: 138830 | N13: 55.78 | O13: =J13/K13 -> 10.557635 | P13: =J13/L13 -> 16.122621 | Q13: =E13/(M13/F13) -> 24.861164 | R13: =E13/N13 -> 8.3313015
B14: Oracle Corporation | C14: ORCL | D14: USD | E14: 129.87 | F14: 2986 | G14: =F14*E14 -> 387791.82 | H14: 167430 | I14: =167430-31890 -> 135540 | J14: =G14+I14 -> 523331.82 | K14: 80168 | L14: 46660 | M14: 21529 | N14: 13.04 | O14: =J14/K14 -> 6.5279391 | P14: =J14/L14 -> 11.215856 | Q14: =E14/(M14/F14) -> 18.012533 | R14: =E14/N14 -> 9.9593558
B15: Salesforce, Inc. | C15: CRM | D15: USD | E15: 184.02 | F15: 819 | G15: =F15*E15 -> 150712.38 | H15: 42550 | I15: =42550-11840 -> 30710 | J15: =G15+I15 -> 181422.38 | K15: 45722 | L15: 17405 | M15: 10729 | N15: 41.8 | O15: =J15/K15 -> 3.967945 | P15: =J15/L15 -> 10.423578 | Q15: =E15/(M15/F15) -> 14.047197 | R15: =E15/N15 -> 4.4023923
B16: International Business Machines | C16: IBM | D16: USD | E16: 223.65 | F16: 942 | G16: =F16*E16 -> 210678.3 | H16: 65270 | I16: =65270-8130 -> 57140 | J16: =G16+I16 -> 267818.3 | K16: 70344 | L16: 16172 | M16: 11822 | N16: 35.08 | O16: =J16/K16 -> 3.8072657 | P16: =J16/L16 -> 16.560617 | Q16: =E16/(M16/F16) -> 17.820868 | R16: =E16/N16 -> 6.3754276

Sheet India
B2: Comparable Company Valuation - INDIA
B3: Amount in Crores
E4: Market Data | L4: Financials | Q4: Valuation
B5: S.No. | C5: Company Name | D5: Ticker | E5: Currency | F5: Share Price | G5: Outstanding Share | H5: Equity Value | I5: Total Debt | J5: Net Debt | K5: Enterprise Value | M5: Revenue | N5: EBITDA | O5: Net Income | P5: Book Value | R5: EV/Revenue | S5: EV/EBITDA | T5: P/E | U5: P/B
B6: 1 | C6: ='Raw Data'!C5 -> TCS | D6: TCS | E6: INR | F6: ='Raw Data'!D5 -> 2361 | G6: ='Raw Data'!E5 -> 361.80856 | H6: =G6*F6 -> 854230 | I6: ='Raw Data'!G5 -> 10821 | J6: ='Raw Data'!I5 -> -45922 | K6: =H6+J6 -> 808308 | M6: ='Raw Data'!K5 -> 275859 | N6: ='Raw Data'!M5 -> 68850.767 | O6: ='Raw Data'!N5 -> 50055 | P6: ='Raw Data'!O5 -> 296 | R6: =K6/M6 -> 2.9301491 | S6: =K6/N6 -> 11.74 | T6: =H6/O6 -> 17.065828
B7: 2 | C7: ='Raw Data'!C6 -> Infosys | D7: INFY | E7: INR | F7: ='Raw Data'!D6 -> 1169.2 | G7: ='Raw Data'!E6 -> 405.80568 | H7: =G7*F7 -> 474468 | I7: ='Raw Data'!G6 -> 8788 | J7: ='Raw Data'!I6 -> -18034 | K7: =H7+J7 -> 456434 | M7: ='Raw Data'!K6 -> 184582 | N7: ='Raw Data'!M6 -> 48973.605 | O7: ='Raw Data'!N6 -> 30325 | P7: ='Raw Data'!O6 -> 228.68 | R7: =K7/M7 -> 2.472798 | S7: =K7/N7 -> 9.32 | T7: =H7/O7 -> 15.646101
B8: 3 | C8: ='Raw Data'!C7 -> Wipro Ltd | D8: WIPRO | E8: INR | F8: ='Raw Data'!D7 -> 184 | G8: ='Raw Data'!E7 -> 990.44022 | H8: =G8*F8 -> 182241 | I8: ='Raw Data'!G7 -> 20291 | J8: ='Raw Data'!I7 -> -34033 | K8: =H8+J8 -> 148208 | M8: ='Raw Data'!K7 -> 94968 | N8: ='Raw Data'!M7 -> 14645.059 | O8: ='Raw Data'!N7 -> 13285 | P8: ='Raw Data'!O7 -> 83.9 | R8: =K8/M8 -> 1.5606099 | S8: =K8/N8 -> 10.12 | T8: =H8/O8 -> 13.717802
B10: High | R10: =MAX(R6:R8) -> 2.9301491 | S10: =MAX(S6:S8) -> 11.74 | T10: =MAX(T6:T8) -> 17.065828
B11: 75th Percentile | R11: =QUARTILE(R6:R8,3) -> 2.7014735 | S11: =QUARTILE(S6:S8,3) -> 10.93 | T11: =QUARTILE(T6:T8,3) -> 16.355964
B12: Average | R12: =AVERAGE(R6:R8) -> 2.3211857 | S12: =AVERAGE(S6:S8) -> 10.393333 | T12: =AVERAGE(T6:T8) -> 15.476577
B13: Median | R13: =MEDIAN(R6:R8) -> 2.472798 | S13: =MEDIAN(S6:S8) -> 10.12 | T13: =MEDIAN(T6:T8) -> 15.646101
B14: 25th Percentile | R14: =QUARTILE(R6:R8,1) -> 2.0167039 | S14: =QUARTILE(S6:S8,1) -> 9.72 | T14: =QUARTILE(T6:T8,1) -> 14.681951
B15: Low | R15: =MIN(R6:R8) -> 1.5606099 | S15: =MIN(S6:S8) -> 9.32 | T15: =MIN(T6:T8) -> 13.717802
B17: TCS Comparable Valuation
B18: Implied Enterprise Value | R18: =R13*M6 -> 682143.58 | S18: =S13*N6 -> 696769.76
B19: Net Debt | R19: =$J$6 -> -45922 | S19: =$J$6 -> -45922
B20: Implied Market Value | R20: =R18-R19 -> 728065.58 | S20: =S18-S19 -> 742691.76 | T20: =T13*O6 -> 783165.56
B21: Outstanding Share | R21: =$G$6 -> 361.80856 | S21: =$G$6 -> 361.80856 | T21: =$G$6 -> 361.80856
B23: Implied Value per Share | R23: =R20/R21 -> 2012.2951 | S23: =S20/S21 -> 2052.7203 | T23: =T20/T21 -> 2164.5855
B25: Source: screener.in, StockAnalysis.com (see 'Raw Data' sheet cell comments for full citations) | R25: =IF(R23>$F$6,"Undervalued","Overvalued") -> Overvalued | S25: =IF(S23>$F$6,"Undervalued","Overvalued") -> Overvalued | T25: =IF(T23>$F$6,"Undervalued","Overvalued") -> Overvalued

Sheet IND - Dashboard
B3: Tata Consultancy Services Ltd | N3: NSE:TCS | S3: Interpretation
B4: Relative Valuation | S4: ="• "&B3&" currently trades at "&TEXT(India!S6,"0.00")&"x EV/EBITDA, "&TEXT(India!R6,"0.00")&"x EV/Revenue and "&TEXT(India!T6,"0.00")&"x P/E, compared with peer medians (excl. "&B3&") of "&TEXT($D$8,"0.00")&"x, "&TEXT($F$8,"0.00")&"x and "&TEXT($H$8,"0.00")&"x respectively." -> • Tata Consultancy Services Ltd currently trades at 11.74x EV/EBITDA, 2.93x EV/Revenue and 17.07x P/E, compared with peer medians (excl. Tata Consultancy Services Ltd) of 9.72x, 2.02x and 14.68x respectively.
B5: Indian IT services comparables | Market data per Raw Data sheet | Financial values in Crore INR
B8: =India!F6 -> 2361 | D8: =MEDIAN(India!S7,India!S8) -> 9.72 | F8: =MEDIAN(India!R7,India!R8) -> 2.0167039 | H8: =MEDIAN(India!T7,India!T8) -> 14.681951 | J8: =IF(F36>B8,"Undervalued","Overvalued") -> Overvalued
B10: Current Share Price | D10: Peer Median EV/EBITDA | F10: Peer Median EV/Revenue | H10: Peer Median P/E | S10: ="• Peer-implied values range from "&"₹"&TEXT(MIN($F$33:$F$35),"#,##0")&" to "&"₹"&TEXT(MAX($F$33:$F$35),"#,##0")&", averaging "&"₹"&TEXT($F$36,"#,##0")&" versus the current price of "&"₹"&TEXT($B$8,"#,##0")&" — indicating "&TEXT(ABS($F$37),"0.0%")&" "&IF($F$37<0,"downside","upside")&" to the average peer-implied value." -> • Peer-implied values range from ₹1,665 to ₹2,031, averaging ₹1,891 versus the current price of ₹2,361 — indicating 19.9% downside to the average peer-implied value.
S17: ="• The verdict of '"&$J$8&"' reflects where the average peer-implied value sits versus the current price; the gap is widest on the "&IF(ABS($F$34/$B$8-1)>=ABS($F$33/$B$8-1),IF(ABS($F$34/$B$8-1)>=ABS($F$35/$B$8-1),"EV/Revenue","P/E"),IF(ABS($F$33/$B$8-1)>=ABS($F$35/$B$8-1),"EV/EBITDA","P/E"))&" multiple." -> • The verdict of 'Overvalued' reflects where the average peer-implied value sits versus the current price; the gap is widest on the EV/Revenue multiple.
S23: • A premium to peers can reflect expectations of stronger growth, margin durability or execution; any earnings miss, multiple de-rating across the sector, or slower-than-expected delivery would narrow or reverse this gap. This is a mechanical comps-based read and not a price target.
B31: Supporting Valuation Calculations (peer group excludes subject company)
B32: Method | D32: Peer Median Multiple | F32: Implied Value / Share (₹) | H32: Market Price
B33: EV/EBITDA basis | D33: =D8 -> 9.72 | F33: =(D8*India!N6-India!J6)/India!G6 -> 1976.6018 | H33: =$B$8 -> 2361
B34: EV/Revenue basis | D34: =F8 -> 2.0167039 | F34: =(F8*India!M6-India!J6)/India!G6 -> 1664.5486 | H34: =$B$8 -> 2361
B35: P/E basis | D35: =H8 -> 14.681951 | F35: =H8*India!O6/India!G6 -> 2031.1987 | H35: =$B$8 -> 2361
B36: Average implied value | F36: =AVERAGE(F33:F35) -> 1890.7831
B37: Upside / (Downside) to CMP | F37: =F36/B8-1 -> -0.19916008
B39: Peer group for chart & KPI medians excludes TCS itself (Infosys, Wipro only). Source data and full comp set: 'India' and 'Raw Data' sheets.
B45: Chart Data (EV/EBITDA)
B46: TCS | C46: =India!S6 -> 11.74 | D46: =$D$8 -> 9.72
B47: Infosys | C47: =India!S7 -> 9.32 | D47: =$D$8 -> 9.72
B48: Wipro | C48: =India!S8 -> 10.12 | D48: =$D$8 -> 9.72
B50: Chart Data (P/E)
B51: TCS | C51: =India!T6 -> 17.065828 | D51: =$H$8 -> 14.681951
B52: Infosys | C52: =India!T7 -> 15.646101 | D52: =$H$8 -> 14.681951
B53: Wipro | C53: =India!T8 -> 13.717802 | D53: =$H$8 -> 14.681951

Sheet US
B2: Comparable Company Valuation - US
B3: Amount in $ Million
E4: Market Data | L4: Financials | Q4: Valuation
B5: Company Name | C5: Ticker | D5: Currency | E5: Share Price | F5: Outstanding Share | G5: Equity Value | H5: Total Debt | I5: Net Debt | J5: Enterprise Value | L5: Revenue | M5: EBITDA | N5: Net Income | O5: Book Value | Q5: EV/Revenue | R5: EV/EBITDA | S5: P/E | T5: P/B
B6: ='Raw Data'!B12 -> Alphabet Inc. | C6: ='Raw Data'!C12 -> GOOGL | D6: USD | E6: ='Raw Data'!E12 -> 356.13 | F6: ='Raw Data'!F12 -> 12230 | G6: =F6*E6 -> 4355469.9 | H6: ='Raw Data'!H12 -> 120790 | I6: ='Raw Data'!I12 -> -121680 | J6: =G6+I6 -> 4233789.9 | L6: ='Raw Data'!K12 -> 497700 | M6: ='Raw Data'!L12 -> 173200 | N6: ='Raw Data'!M12 -> 175134 | O6: ='Raw Data'!N12 -> 50.9 | Q6: =J6/L6 -> 8.5067107 | R6: =J6/M6 -> 24.444514 | S6: ='Raw Data'!Q12 -> 24.869357 | T6: =E6/O6 -> 6.9966601
B7: ='Raw Data'!B13 -> Microsoft Corporation | C7: ='Raw Data'!C13 -> MSFT | D7: USD | E7: ='Raw Data'!E13 -> 464.72 | F7: ='Raw Data'!F13 -> 7427 | G7: =F7*E7 -> 3451475.4 | H7: ='Raw Data'!H13 -> 128813 | I7: ='Raw Data'!I13 -> 51970 | J7: =G7+I7 -> 3503445.4 | L7: ='Raw Data'!K13 -> 331840 | M7: ='Raw Data'!L13 -> 217300 | N7: ='Raw Data'!M13 -> 138830 | O7: ='Raw Data'!N13 -> 55.78 | Q7: =J7/L7 -> 10.557635 | R7: =J7/M7 -> 16.122621 | S7: ='Raw Data'!Q13 -> 24.861164 | T7: =E7/O7 -> 8.3313015
B8: ='Raw Data'!B14 -> Oracle Corporation | C8: ='Raw Data'!C14 -> ORCL | D8: USD | E8: ='Raw Data'!E14 -> 129.87 | F8: ='Raw Data'!F14 -> 2986 | G8: =F8*E8 -> 387791.82 | H8: ='Raw Data'!H14 -> 167430 | I8: ='Raw Data'!I14 -> 135540 | J8: =G8+I8 -> 523331.82 | L8: ='Raw Data'!K14 -> 80168 | M8: ='Raw Data'!L14 -> 46660 | N8: ='Raw Data'!M14 -> 21529 | O8: ='Raw Data'!N14 -> 13.04 | Q8: =J8/L8 -> 6.5279391 | R8: =J8/M8 -> 11.215856 | S8: ='Raw Data'!Q14 -> 18.012533 | T8: =E8/O8 -> 9.9593558
B9: ='Raw Data'!B15 -> Salesforce, Inc. | C9: ='Raw Data'!C15 -> CRM | D9: USD | E9: ='Raw Data'!E15 -> 184.02 | F9: ='Raw Data'!F15 -> 819 | G9: =F9*E9 -> 150712.38 | H9: ='Raw Data'!H15 -> 42550 | I9: ='Raw Data'!I15 -> 30710 | J9: =G9+I9 -> 181422.38 | L9: ='Raw Data'!K15 -> 45722 | M9: ='Raw Data'!L15 -> 17405 | N9: ='Raw Data'!M15 -> 10729 | O9: ='Raw Data'!N15 -> 41.8 | Q9: =J9/L9 -> 3.967945 | R9: =J9/M9 -> 10.423578 | S9: ='Raw Data'!Q15 -> 14.047197 | T9: =E9/O9 -> 4.4023923
B10: ='Raw Data'!B16 -> International Business Machines | C10: ='Raw Data'!C16 -> IBM | D10: USD | E10: ='Raw Data'!E16 -> 223.65 | F10: ='Raw Data'!F16 -> 942 | G10: =F10*E10 -> 210678.3 | H10: ='Raw Data'!H16 -> 65270 | I10: ='Raw Data'!I16 -> 57140 | J10: =G10+I10 -> 267818.3 | L10: ='Raw Data'!K16 -> 70344 | M10: ='Raw Data'!L16 -> 16172 | N10: ='Raw Data'!M16 -> 11822 | O10: ='Raw Data'!N16 -> 35.08 | Q10: =J10/L10 -> 3.8072657 | R10: =J10/M10 -> 16.560617 | S10: ='Raw Data'!Q16 -> 17.820868 | T10: =E10/O10 -> 6.3754276
B12: High | Q12: =MAX(Q6:Q10) -> 10.557635 | R12: =MAX(R6:R10) -> 24.444514 | S12: =MAX(S6:S10) -> 24.869357
B13: 75th Percentile | Q13: =QUARTILE(Q6:Q10,3) -> 8.5067107 | R13: =QUARTILE(R6:R10,3) -> 16.560617 | S13: =QUARTILE(S6:S10,3) -> 24.861164
B14: Average | Q14: =AVERAGE(Q6:Q10) -> 6.673499 | R14: =AVERAGE(R6:R10) -> 15.753437 | S14: =AVERAGE(S6:S10) -> 19.922224
B15: Median | Q15: =MEDIAN(Q6:Q10) -> 6.5279391 | R15: =MEDIAN(R6:R10) -> 16.122621 | S15: =MEDIAN(S6:S10) -> 18.012533
B16: 25th Percentile | Q16: =QUARTILE(Q6:Q10,1) -> 3.967945 | R16: =QUARTILE(R6:R10,1) -> 11.215856 | S16: =QUARTILE(S6:S10,1) -> 17.820868
B17: Low | Q17: =MIN(Q6:Q10) -> 3.8072657 | R17: =MIN(R6:R10) -> 10.423578 | S17: =MIN(S6:S10) -> 14.047197
B19: Microsoft Comparable Valuation
B20: Implied Enterprise Value | Q20: =Q15*L7 -> 2166231.3 | R20: =R15*M7 -> 3503445.4
B21: Net Debt | Q21: =$I$7 -> 51970 | R21: =$I$7 -> 51970
B22: Implied Market Value | Q22: =Q20-Q21 -> 2114261.3 | R22: =R20-R21 -> 3451475.4 | S22: =S15*N7 -> 2500679.9
B23: Outstanding Share | Q23: =$F$7 -> 7427 | R23: =$F$7 -> 7427 | S23: =$F$7 -> 7427
B25: Implied Value per Share | Q25: =Q22/Q23 -> 284.67232 | R25: =R22/R23 -> 464.72 | S25: =S22/S23 -> 336.70122
B27: Source: StockAnalysis.com, finbox.com, GuruFocus, Simply Wall St (see 'Raw Data' sheet cell comments for full citations) | Q27: =IF(Q25<$E$7,"Overvalued","Undervalued") -> Overvalued | R27: =IF(R25<$E$7,"Overvalued","Undervalued") -> Undervalued | S27: =IF(S25<$E$7,"Overvalued","Undervalued") -> Overvalued

Sheet US - Dashboard
B3: Microsoft Corporation | N3: NASDAQ:MSFT | S3: Interpretation
B4: Relative Valuation | S4: ="• "&B3&" currently trades at "&TEXT(US!R7,"0.00")&"x EV/EBITDA, "&TEXT(US!Q7,"0.00")&"x EV/Revenue and "&TEXT(US!S7,"0.00")&"x P/E, compared with peer medians (excl. "&B3&") of "&TEXT($D$8,"0.00")&"x, "&TEXT($F$8,"0.00")&"x and "&TEXT($H$8,"0.00")&"x respectively." -> • Microsoft Corporation currently trades at 16.12x EV/EBITDA, 10.56x EV/Revenue and 24.86x P/E, compared with peer medians (excl. Microsoft Corporation) of 13.89x, 5.25x and 17.92x respectively.
B5: US technology mega-cap comparables | Market data per Raw Data sheet | Financial values in $ Million
B8: =US!E7 -> 464.72 | D8: =MEDIAN(US!R6,US!R8,US!R9,US!R10) -> 13.888236 | F8: =MEDIAN(US!Q6,US!Q8,US!Q9,US!Q10) -> 5.247942 | H8: =MEDIAN(US!S6,US!S8,US!S9,US!S10) -> 17.9167 | J8: =IF(F36>B8,"Undervalued","Overvalued") -> Overvalued
B10: Current Share Price | D10: Peer Median EV/EBITDA | F10: Peer Median EV/Revenue | H10: Peer Median P/E | S10: ="• Peer-implied values range from "&"$"&TEXT(MIN($F$33:$F$35),"#,##0")&" to "&"$"&TEXT(MAX($F$33:$F$35),"#,##0")&", averaging "&"$"&TEXT($F$36,"#,##0")&" versus the current price of "&"$"&TEXT($B$8,"#,##0")&" — indicating "&TEXT(ABS($F$37),"0.0%")&" "&IF($F$37<0,"downside","upside")&" to the average peer-implied value." -> • Peer-implied values range from $227 to $399, averaging $321 versus the current price of $465 — indicating 31.0% downside to the average peer-implied value.
S17: ="• The verdict of '"&$J$8&"' reflects where the average peer-implied value sits versus the current price; the gap is widest on the "&IF(ABS($F$34/$B$8-1)>=ABS($F$33/$B$8-1),IF(ABS($F$34/$B$8-1)>=ABS($F$35/$B$8-1),"EV/Revenue","P/E"),IF(ABS($F$33/$B$8-1)>=ABS($F$35/$B$8-1),"EV/EBITDA","P/E"))&" multiple." -> • The verdict of 'Overvalued' reflects where the average peer-implied value sits versus the current price; the gap is widest on the EV/Revenue multiple.
S23: • A premium to peers can reflect expectations of stronger growth, margin durability or execution; any earnings miss, multiple de-rating across the sector, or slower-than-expected delivery would narrow or reverse this gap. This is a mechanical comps-based read and not a price target.
B31: Supporting Valuation Calculations (peer group excludes subject company)
B32: Method | D32: Peer Median Multiple | F32: Implied Value / Share ($) | H32: Market Price
B33: EV/EBITDA basis | D33: =D8 -> 13.888236 | F33: =(D8*US!M7-US!I7)/US!F7 -> 399.34614 | H33: =$B$8 -> 464.72
B34: EV/Revenue basis | D34: =F8 -> 5.247942 | F34: =(F8*US!L7-US!I7)/US!F7 -> 227.48177 | H34: =$B$8 -> 464.72
B35: P/E basis | D35: =H8 -> 17.9167 | F35: =H8*US!N7/US!F7 -> 334.90986 | H35: =$B$8 -> 464.72
B36: Average implied value | F36: =AVERAGE(F33:F35) -> 320.57925
B37: Upside / (Downside) to CMP | F37: =F36/B8-1 -> -0.31016687
B39: Peer group for chart & KPI medians excludes MSFT itself (Alphabet, Oracle, Salesforce, IBM only). Source data and full comp set: 'US' and 'Raw Data' sheets.
B45: Chart Data (EV/EBITDA)
B46: MSFT | C46: =US!R7 -> 16.122621 | D46: =$D$8 -> 13.888236
B47: Alphabet | C47: =US!R6 -> 24.444514 | D47: =$D$8 -> 13.888236
B48: Oracle | C48: =US!R8 -> 11.215856 | D48: =$D$8 -> 13.888236
B49: Salesforce | C49: =US!R9 -> 10.423578 | D49: =$D$8 -> 13.888236
B50: IBM | C50: =US!R10 -> 16.560617 | D50: =$D$8 -> 13.888236
B52: Chart Data (P/E)
B53: MSFT | C53: =US!S7 -> 24.861164 | D53: =$H$8 -> 17.9167
B54: Alphabet | C54: =US!S6 -> 24.869357 | D54: =$H$8 -> 17.9167
B55: Oracle | C55: =US!S8 -> 18.012533 | D55: =$H$8 -> 17.9167
B56: Salesforce | C56: =US!S9 -> 14.047197 | D56: =$H$8 -> 17.9167
B57: IBM | C57: =US!S10 -> 17.820868 | D57: =$H$8 -> 17.9167

Sheet PROMPT
A1: You are helping me build the Enterprise Value (EV) bridge for a trading comparables
A2: analysis.
A4: COMPANY: {COMPANY NAME} (Ticker: {TICKER}, Exchange: {EXCHANGE})
A5: AS-OF DATE: 31-Jul-2026
A7: TASK:
A9: 1. Identify the latest filing available as of 31-Jul-2026 (10-K, 10-Q, annual report,
A10: or quarterly/annual results filed with the relevant exchange — e.g. BSE/NSE for
A11: Indian companies, SEC/EDGAR for US companies). State the filing type, the period
A12: it covers, and its filing date.
A14: 2. Identify the reporting date (the balance sheet date the figures below are drawn
A15: from — this may differ from the filing date).
A17: 3. Extract SHARES OUTSTANDING — state whether this is diluted weighted-average shares
... A86: presentation, annual report notes, or a request to the company's IR team).
